oceanlab_api_client/__init__.py
oceanlab_api_client/api/__init__.py
oceanlab_api_client/api/node2/__init__.py
oceanlab_api_client/api/node2/ais.py
oceanlab_api_client/api/node3/__init__.py
oceanlab_api_client/api/node3/raw_data_node3.py
oceanlab_api_client/api/node3/tags.py
oceanlab_api_client/api/node4/__init__.py
oceanlab_api_client/api/node4/aggregated_data.py
oceanlab_api_client/api/node4/measurement_columns.py
oceanlab_api_client/api/node4/measurements.py
oceanlab_api_client/api/node4/raw_data_all.py
oceanlab_api_client/api/node4/raw_data_count.py
oceanlab_api_client/api/node4/raw_data_dates.py
oceanlab_api_client/api/node4/raw_data_node4.py
oceanlab_api_client/client.py
oceanlab_api_client/errors.py
oceanlab_api_client/models/__init__.py
oceanlab_api_client/models/aggregated_data_response_200.py
oceanlab_api_client/models/aggregated_data_response_200_response.py
oceanlab_api_client/models/aggregated_data_response_200_response_result_item.py
oceanlab_api_client/models/aggregated_data_response_200_response_status_item.py
oceanlab_api_client/models/ais_response_200.py
oceanlab_api_client/models/ais_response_200_response.py
oceanlab_api_client/models/ais_response_200_response_result_item.py
oceanlab_api_client/models/ais_response_200_response_status_item.py
oceanlab_api_client/models/measurement_columns_response_200.py
oceanlab_api_client/models/measurement_columns_response_200_response.py
oceanlab_api_client/models/measurement_columns_response_200_response_result_item.py
oceanlab_api_client/models/measurement_columns_response_200_response_status_item.py
oceanlab_api_client/models/measurements_response_200.py
oceanlab_api_client/models/measurements_response_200_response.py
oceanlab_api_client/models/measurements_response_200_response_result_item.py
oceanlab_api_client/models/measurements_response_200_response_status_item.py
oceanlab_api_client/models/raw_data_all_response_200.py
oceanlab_api_client/models/raw_data_all_response_200_response.py
oceanlab_api_client-1.2.0.dist-info/METADATA
oceanlab_api_client-1.2.0.dist-info/WHEEL
oceanlab_api_client-1.2.0.dist-info/RECORD
